gstreamer_python/__init__.py
gstreamer_python/Lib/girepository-1.0/GdkPixbuf-2.0.typelib
gstreamer_python/Lib/girepository-1.0/HarfBuzz-0.0.typelib
gstreamer_python/Lib/girepository-1.0/Json-1.0.typelib
gstreamer_python/Lib/girepository-1.0/Pango-1.0.typelib
gstreamer_python/Lib/girepository-1.0/PangoCairo-1.0.typelib
gstreamer_python/Lib/girepository-1.0/Soup-3.0.typelib
gstreamer_python/Lib/gstreamer-1.0/gstpython.dll
gstreamer_python/Lib/site-packages/cairo/__init__.py
gstreamer_python/Lib/site-packages/cairo/__init__.pyi
gstreamer_python/Lib/site-packages/cairo/_cairo.cp314-win_amd64.pyd
gstreamer_python/Lib/site-packages/cairo/py.typed
gstreamer_python/Lib/site-packages/cairo/include/py3cairo.h
gstreamer_python/Lib/site-packages/gi/__init__.py
gstreamer_python/Lib/site-packages/gi/_constants.py
gstreamer_python/Lib/site-packages/gi/_error.py
gstreamer_python/Lib/site-packages/gi/_gi.cp314-win_amd64.pyd
gstreamer_python/Lib/site-packages/gi/_gi_cairo.cp314-win_amd64.pyd
gstreamer_python/Lib/site-packages/gi/_gtktemplate.py
gstreamer_python/Lib/site-packages/gi/_option.py
gstreamer_python/Lib/site-packages/gi/_ossighelper.py
gstreamer_python/Lib/site-packages/gi/_propertyhelper.py
gstreamer_python/Lib/site-packages/gi/_signalhelper.py
gstreamer_python/Lib/site-packages/gi/docstring.py
gstreamer_python/Lib/site-packages/gi/events.py
gstreamer_python/Lib/site-packages/gi/importer.py
gstreamer_python/Lib/site-packages/gi/module.py
gstreamer_python/Lib/site-packages/gi/pygtkcompat.py
gstreamer_python/Lib/site-packages/gi/types.py
gstreamer_python/Lib/site-packages/gi/overrides/GES.py
gstreamer_python/Lib/site-packages/gi/overrides/GIMarshallingTests.py
gstreamer_python/Lib/site-packages/gi/overrides/GLib.py
gstreamer_python/Lib/site-packages/gi/overrides/GObject.py
gstreamer_python/Lib/site-packages/gi/overrides/Gdk.py
gstreamer_python/Lib/site-packages/gi/overrides/GdkPixbuf.py
gstreamer_python/Lib/site-packages/gi/overrides/Gio.py
gstreamer_python-1.27.90.dist-info/METADATA
gstreamer_python-1.27.90.dist-info/WHEEL
gstreamer_python-1.27.90.dist-info/top_level.txt
gstreamer_python/Lib/site-packages/PyGObject-3.50.2.dist-info/METADATA
gstreamer_python/Lib/site-packages/pycairo-1.27.0.dist-info/METADATA
gstreamer_python-1.27.90.dist-info/RECORD
